headlessai/__init__.py
headlessai/hello.py
headlessai-0.1.0.dist-info/METADATA
headlessai-0.1.0.dist-info/WHEEL
headlessai-0.1.0.dist-info/top_level.txt
headlessai-0.1.0.dist-info/RECORD
